RTL/MISR.v
module misr(
    input  wire clk,
    input  wire reset_n,
    input  wire enable,
    input  wire data_in,
    output reg  signature
);

    always @(posedge clk or negedge reset_n) begin
        if (!reset_n)
            signature <= 1'b0;
        else if (enable)
            signature <= signature ^ data_in;
    end

endmodule

RTL/LC.v
module layer_connections(
    input  wire clk,
    input  wire reset_n,
    input  wire enable,
    input  wire scan_in,
    output reg  scan_out
);

    always @(posedge clk or negedge reset_n) begin
        if (!reset_n)
            scan_out <= 1'b0;
        else if (enable)
            scan_out <= scan_in;
    end

endmodule

RTL/PRAS.v
module pras_block(
    input  wire clk,
    input  wire reset_n,
    input  wire enable,
    input  wire [3:0] col_addr,
    output reg  scan_out
);
    reg [15:0] grid;

    always @(posedge clk or negedge reset_n) begin
        if (!reset_n)
            grid <= 16'hA5A5; 
        else if (enable)
            scan_out <= grid[col_addr];
    end
endmodule

RTL/MSS.v
module mss_block(
    input  wire clk,
    input  wire reset_n,
    input  wire enable,
    input  wire scan_in,
    input  wire [1:0] cluster_sel,
    output wire scan_out
);

    reg [7:0] scan_chain;

    always @(posedge clk or negedge reset_n) begin
        if (!reset_n)
            scan_chain <= 8'b0;
        else if (enable)
            scan_chain <= {scan_chain[6:0], scan_in};
    end

    assign scan_out = scan_chain[7];

endmodule

RTL/TIER_BLOCK.v
module tier_block #(
    parameter TIER_ID = 2'b01
)(
    input  wire       scan_clk,
    input  wire       reset_n,
    input  wire [1:0] tier_sel,
    input  wire [1:0] mode_sel,
    input  wire [3:0] col_addr,
    input  wire [1:0] cluster_sel,
    input  wire       shift_en,
    input  wire       capture_en,
    input  wire       test_en,
    input  wire       scan_in,
    output wire       misr_out
);

    wire active = (tier_sel == TIER_ID) && test_en;

    wire sas_out;
    wire ras_out;
    wire tsv_out;

    // SAS (Serial)
    mss_block MSS (
        .clk(scan_clk),
        .reset_n(reset_n),
        .enable(active && (mode_sel==2'b00)),
        .scan_in(scan_in),
        .cluster_sel(cluster_sel),
        .scan_out(sas_out)
    );

    // RAS
    pras_block PRAS (
        .clk(scan_clk),
        .reset_n(reset_n),
        .enable(active && (mode_sel==2'b01)),
        .col_addr(col_addr),
        .scan_out(ras_out)
    );

    // TSV Wrapper
    layer_connections LC (
        .clk(scan_clk),
        .reset_n(reset_n),
        .enable(active && (mode_sel==2'b10)),
        .scan_in(scan_in),
        .scan_out(tsv_out)
    );

    // Mode MUX
    wire scan_data =
        (mode_sel==2'b00) ? sas_out :
        (mode_sel==2'b01) ? ras_out :
                            tsv_out;
    // MISR
    misr MISR (
        .clk(scan_clk),
        .reset_n(reset_n),
        .enable(capture_en && active),
        .data_in(scan_data),
        .signature(misr_out)
    );

endmodule

RTL/GTC.v
module global_test_controller(
    input  wire       scan_clk,
    input  wire       reset_n,
    input  wire       scan_in,
    input  wire       test_enable,

    output reg [1:0]  tier_sel,
    output reg [1:0]  mode_sel,
    output reg [3:0]  col_addr,
    output reg [1:0]  cluster_sel,
    output reg        shift_en,
    output reg        capture_en,
    output wire       test_en,
    output wire       tsv_scan_in,

    input  wire       misr_t1,
    input  wire       misr_t2,
    input  wire       misr_t3,
    output reg        fault_flag
);

    assign test_en = test_enable;
    assign tsv_scan_in = scan_in;

    always @(posedge scan_clk or negedge reset_n) begin
        if (!reset_n) begin
            tier_sel    <= 2'b01;
            mode_sel    <= 2'b00;  
            col_addr    <= 4'd0;
            cluster_sel <= 2'd0;
            shift_en    <= 1'b0;
            capture_en  <= 1'b0;
            fault_flag  <= 1'b0;
        end 
        else if (test_enable) begin
            shift_en   <= ~shift_en;
            capture_en <= shift_en;
            
            // Allow counters to increment naturally
            col_addr   <= col_addr + 1'b1;
            cluster_sel<= cluster_sel + 1'b1;

            // Cycle Tier Selection
            if (tier_sel == 2'b01)
                tier_sel <= 2'b10;
            else if (tier_sel == 2'b10)
                tier_sel <= 2'b11;
            else
                tier_sel <= 2'b01;

            if (col_addr == 4'hF) begin
                if (mode_sel == 2'b10)
                    mode_sel <= 2'b00;
                else
                    mode_sel <= mode_sel + 1'b1;
            end

            // MISR Aggregation
            fault_flag <= misr_t1 | misr_t2 | misr_t3;
        end
    end

endmodule

RTL/JSCAN_TOP.v
module top_3d_jscan (
    input  wire        scan_clk,
    input  wire        reset_n,
    input  wire        scan_in,
    input  wire        test_enable,
    output wire        fault_flag
);

    // Adding (* keep = "true" *) prevents Vivado from optimizing these out
    (* keep = "true" *) wire [1:0] tier_sel;
    (* keep = "true" *) wire [1:0] mode_sel;
    (* keep = "true" *) wire [3:0] col_addr;
    (* keep = "true" *) wire [1:0] cluster_sel;
    (* keep = "true" *) wire       shift_en;
    (* keep = "true" *) wire       capture_en;
    (* keep = "true" *) wire       test_en;
    (* keep = "true" *) wire       tsv_scan_in;

    wire misr_out_t1, misr_out_t2, misr_out_t3;

    global_test_controller GTC (
        .scan_clk(scan_clk), .reset_n(reset_n), .scan_in(scan_in),
        .test_enable(test_enable), .tier_sel(tier_sel), .mode_sel(mode_sel),
        .col_addr(col_addr), .cluster_sel(cluster_sel), .shift_en(shift_en),
        .capture_en(capture_en), .test_en(test_en), .tsv_scan_in(tsv_scan_in),
        .misr_t1(misr_out_t1), .misr_t2(misr_out_t2), .misr_t3(misr_out_t3),
        .fault_flag(fault_flag)
    );

    // Ensure instances are not optimized away 
    tier_block #(.TIER_ID(2'b01)) TIER1 (
        .scan_clk(scan_clk), .reset_n(reset_n), .tier_sel(tier_sel),
        .mode_sel(mode_sel), .col_addr(col_addr), .cluster_sel(cluster_sel),
        .shift_en(shift_en), .capture_en(capture_en), .test_en(test_en),
        .scan_in(tsv_scan_in), .misr_out(misr_out_t1)
    );

    tier_block #(.TIER_ID(2'b10)) TIER2 (
        .scan_clk(scan_clk), .reset_n(reset_n), .tier_sel(tier_sel),
        .mode_sel(mode_sel), .col_addr(col_addr), .cluster_sel(cluster_sel),
        .shift_en(shift_en), .capture_en(capture_en), .test_en(test_en),
        .scan_in(tsv_scan_in), .misr_out(misr_out_t2)
    );

    tier_block #(.TIER_ID(2'b11)) TIER3 (
        .scan_clk(scan_clk), .reset_n(reset_n), .tier_sel(tier_sel),
        .mode_sel(mode_sel), .col_addr(col_addr), .cluster_sel(cluster_sel),
        .shift_en(shift_en), .capture_en(capture_en), .test_en(test_en),
        .scan_in(tsv_scan_in), .misr_out(misr_out_t3)
    );

endmodule

RTL/JSCAN_TB.v
`timescale 1ns / 1ps

module tb_top_3d_jscan;

    // ----------------------------------------------------------------
    // Signals
    // ----------------------------------------------------------------
    reg  scan_clk;
    reg  reset_n;
    reg  scan_in;
    reg  test_enable;
    wire fault_flag;

    // ----------------------------------------------------------------
    // Device Under Test (DUT)
    // ----------------------------------------------------------------
    top_3d_jscan uut (
        .scan_clk(scan_clk),
        .reset_n(reset_n),
        .scan_in(scan_in),
        .test_enable(test_enable),
        .fault_flag(fault_flag)
    );

    // ----------------------------------------------------------------
    // Clock Generation (100 MHz)
    // ----------------------------------------------------------------
    initial begin
        scan_clk = 0;
        forever #5 scan_clk = ~scan_clk;
    end

    // ----------------------------------------------------------------
    // Test Sequence
    // ----------------------------------------------------------------
    initial begin
        // Initialize Inputs
        reset_n = 1'b1;
        scan_in = 1'b0;
        test_enable = 1'b0;

        $display("--- Starting 3D-JSCAN Corner Case Verification ---");

        $display("[Time: %0t] Case 1: Applying Asynchronous Reset", $time);
        #7 reset_n = 1'b0; // Drop reset mid-cycle
        #10 reset_n = 1'b1;
        
        // ------------------------------------------------------------
        // CASE 2: Normal Operation & Tier Rollover
        // ------------------------------------------------------------
        $display("[Time: %0t] Case 2: Mode and Tier/Col Rollover", $time);
        test_enable = 1'b1;
        
        // Feed a specific sequence to scan_in to build MISR signatures
        repeat(30) begin
            @(negedge scan_clk);
            scan_in = $random % 2; 
        end
        // By 30 cycles, tier_sel (01->10->11->01) and col_addr (4-bit rollover) 
        // will have looped multiple times.

        // ------------------------------------------------------------
        // CASE 3: Test Enable De-assertion (Pause/Freeze State)
        // ------------------------------------------------------------
        $display("[Time: %0t] Case 3: Freezing State via test_enable=0", $time);
        @(negedge scan_clk);
        test_enable = 1'b0; // Logic should freeze, shift_en/capture_en hold
        #40; 
        
        // ------------------------------------------------------------
        // CASE 4: Forced SAS Mode (Serial Architecture Scan)
        // ------------------------------------------------------------
        // GTC hardcodes mode_sel to 2'b10. We force it to 2'b00 to test MSS blocks.
        $display("[Time: %0t] Case 4: Forcing SAS Mode (mode_sel = 00)", $time);
        force uut.GTC.mode_sel = 2'b00;
        test_enable = 1'b1;
        
        // Shift 8 bits to fill the 8-bit scan_chain in mss_block
        repeat(12) begin
            @(negedge scan_clk);
            scan_in = ~scan_in; // Alternating 101010 pattern
        end

        // ------------------------------------------------------------
        // CASE 5: Forced RAS Mode (Random Access Scan)
        // ------------------------------------------------------------
        // Force mode_sel to 2'b01 to test PRAS blocks.
        // PRAS grid is hardcoded to 16'h0000 at reset. We force internal grids 
        // to non-zero values to verify dynamic bit selection via col_addr.
        $display("[Time: %0t] Case 5: Forcing RAS Mode (mode_sel = 01)", $time);
        force uut.GTC.mode_sel = 2'b01;
        force uut.TIER1.PRAS.grid = 16'hA5A5;
        force uut.TIER2.PRAS.grid = 16'h5A5A;
        force uut.TIER3.PRAS.grid = 16'hFFFF;
        
        repeat(20) begin
            @(negedge scan_clk);
        end

        // Release forces
        release uut.GTC.mode_sel;
        release uut.TIER1.PRAS.grid;
        release uut.TIER2.PRAS.grid;
        release uut.TIER3.PRAS.grid;

        // ------------------------------------------------------------
        // CASE 6: Mid-Operation Reset Glitch
        // ------------------------------------------------------------
        $display("[Time: %0t] Case 6: Mid-operation async reset", $time);
        #3 reset_n = 1'b0;
        #5 reset_n = 1'b1;
        #20;

        $display("--- Verification Complete ---");
        $finish;
    end

    // ----------------------------------------------------------------
    // Waveform Dumping (for GTKWave / ModelSim / Vivado)
    // ----------------------------------------------------------------
    initial begin
        $dumpfile("jscan_tb.vcd");
        $dumpvars(0, tb_top_3d_jscan);
    end

endmodule

RTL/jscan_tb.vcd
$date
	Mon Feb 23 15:42:53 2026
$end
$version
	Icarus Verilog
$end
$timescale
	1ps
$end
$scope module tb_top_3d_jscan $end
$var wire 1 ! fault_flag $end
$var reg 1 " reset_n $end
$var reg 1 # scan_clk $end
$var reg 1 $ scan_in $end
$var reg 1 % test_enable $end
$scope module uut $end
$var wire 1 " reset_n $end
$var wire 1 # scan_clk $end
$var wire 1 $ scan_in $end
$var wire 1 % test_enable $end
$var wire 1 & tsv_scan_in $end
$var wire 2 ' tier_sel [1:0] $end
$var wire 1 ( test_en $end
$var wire 1 ) shift_en $end
$var wire 2 * mode_sel [1:0] $end
$var wire 1 + misr_out_t3 $end
$var wire 1 , misr_out_t2 $end
$var wire 1 - misr_out_t1 $end
$var wire 1 ! fault_flag $end
$var wire 4 . col_addr [3:0] $end
$var wire 2 / cluster_sel [1:0] $end
$var wire 1 0 capture_en $end
$scope module GTC $end
$var wire 1 " reset_n $end
$var wire 1 # scan_clk $end
$var wire 1 $ scan_in $end
$var wire 1 ( test_en $end
$var wire 1 % test_enable $end
$var wire 1 & tsv_scan_in $end
$var wire 1 + misr_t3 $end
$var wire 1 , misr_t2 $end
$var wire 1 - misr_t1 $end
$var reg 1 0 capture_en $end
$var reg 2 1 cluster_sel [1:0] $end
$var reg 4 2 col_addr [3:0] $end
$var reg 1 ! fault_flag $end
$var reg 2 3 mode_sel [1:0] $end
$var reg 1 ) shift_en $end
$var reg 2 4 tier_sel [1:0] $end
$upscope $end
$scope module TIER1 $end
$var wire 1 5 active $end
$var wire 1 0 capture_en $end
$var wire 2 6 cluster_sel [1:0] $end
$var wire 4 7 col_addr [3:0] $end
$var wire 2 8 mode_sel [1:0] $end
$var wire 1 " reset_n $end
$var wire 1 # scan_clk $end
$var wire 1 & scan_in $end
$var wire 1 ) shift_en $end
$var wire 1 ( test_en $end
$var wire 2 9 tier_sel [1:0] $end
$var wire 1 : tsv_out $end
$var wire 1 ; scan_data $end
$var wire 1 < sas_out $end
$var wire 1 = ras_out $end
$var wire 1 - misr_out $end
$var parameter 2 > TIER_ID $end
$scope module LC $end
$var wire 1 # clk $end
$var wire 1 ? enable $end
$var wire 1 " reset_n $end
$var wire 1 & scan_in $end
$var reg 1 : scan_out $end
$upscope $end
$scope module MISR $end
$var wire 1 # clk $end
$var wire 1 ; data_in $end
$var wire 1 @ enable $end
$var wire 1 " reset_n $end
$var reg 1 - signature $end
$upscope $end
$scope module MSS $end
$var wire 1 # clk $end
$var wire 2 A cluster_sel [1:0] $end
$var wire 1 B enable $end
$var wire 1 " reset_n $end
$var wire 1 & scan_in $end
$var wire 1 < scan_out $end
$var reg 8 C scan_chain [7:0] $end
$upscope $end
$scope module PRAS $end
$var wire 1 # clk $end
$var wire 4 D col_addr [3:0] $end
$var wire 1 E enable $end
$var wire 1 " reset_n $end
$var reg 16 F grid [15:0] $end
$var reg 1 = scan_out $end
$upscope $end
$upscope $end
$scope module TIER2 $end
$var wire 1 G active $end
$var wire 1 0 capture_en $end
$var wire 2 H cluster_sel [1:0] $end
$var wire 4 I col_addr [3:0] $end
$var wire 2 J mode_sel [1:0] $end
$var wire 1 " reset_n $end
$var wire 1 # scan_clk $end
$var wire 1 & scan_in $end
$var wire 1 ) shift_en $end
$var wire 1 ( test_en $end
$var wire 2 K tier_sel [1:0] $end
$var wire 1 L tsv_out $end
$var wire 1 M scan_data $end
$var wire 1 N sas_out $end
$var wire 1 O ras_out $end
$var wire 1 , misr_out $end
$var parameter 2 P TIER_ID $end
$scope module LC $end
$var wire 1 # clk $end
$var wire 1 Q enable $end
$var wire 1 " reset_n $end
$var wire 1 & scan_in $end
$var reg 1 L scan_out $end
$upscope $end
$scope module MISR $end
$var wire 1 # clk $end
$var wire 1 M data_in $end
$var wire 1 R enable $end
$var wire 1 " reset_n $end
$var reg 1 , signature $end
$upscope $end
$scope module MSS $end
$var wire 1 # clk $end
$var wire 2 S cluster_sel [1:0] $end
$var wire 1 T enable $end
$var wire 1 " reset_n $end
$var wire 1 & scan_in $end
$var wire 1 N scan_out $end
$var reg 8 U scan_chain [7:0] $end
$upscope $end
$scope module PRAS $end
$var wire 1 # clk $end
$var wire 4 V col_addr [3:0] $end
$var wire 1 W enable $end
$var wire 1 " reset_n $end
$var reg 16 X grid [15:0] $end
$var reg 1 O scan_out $end
$upscope $end
$upscope $end
$scope module TIER3 $end
$var wire 1 Y active $end
$var wire 1 0 capture_en $end
$var wire 2 Z cluster_sel [1:0] $end
$var wire 4 [ col_addr [3:0] $end
$var wire 2 \ mode_sel [1:0] $end
$var wire 1 " reset_n $end
$var wire 1 # scan_clk $end
$var wire 1 & scan_in $end
$var wire 1 ) shift_en $end
$var wire 1 ( test_en $end
$var wire 2 ] tier_sel [1:0] $end
$var wire 1 ^ tsv_out $end
$var wire 1 _ scan_data $end
$var wire 1 ` sas_out $end
$var wire 1 a ras_out $end
$var wire 1 + misr_out $end
$var parameter 2 b TIER_ID $end
$scope module LC $end
$var wire 1 # clk $end
$var wire 1 c enable $end
$var wire 1 " reset_n $end
$var wire 1 & scan_in $end
$var reg 1 ^ scan_out $end
$upscope $end
$scope module MISR $end
$var wire 1 # clk $end
$var wire 1 _ data_in $end
$var wire 1 d enable $end
$var wire 1 " reset_n $end
$var reg 1 + signature $end
$upscope $end
$scope module MSS $end
$var wire 1 # clk $end
$var wire 2 e cluster_sel [1:0] $end
$var wire 1 f enable $end
$var wire 1 " reset_n $end
$var wire 1 & scan_in $end
$var wire 1 ` scan_out $end
$var reg 8 g scan_chain [7:0] $end
$upscope $end
$scope module PRAS $end
$var wire 1 # clk $end
$var wire 4 h col_addr [3:0] $end
$var wire 1 i enable $end
$var wire 1 " reset_n $end
$var reg 16 j grid [15:0] $end
$var reg 1 a scan_out $end
$upscope $end
$upscope $end
$upscope $end
$upscope $end
$enddefinitions $end
$comment Show the parameter values. $end
$dumpall
b11 b
b10 P
b1 >
$end
#0
$dumpvars
bx j
0i
bx h
bx g
0f
bx e
0d
0c
xa
x`
x_
x^
bx ]
bx \
bx [
bx Z
0Y
bx X
0W
bx V
bx U
0T
bx S
0R
0Q
xO
xN
xM
xL
bx K
bx J
bx I
bx H
0G
bx F
0E
bx D
bx C
0B
bx A
0@
0?
x=
x<
x;
x:
bx 9
bx 8
bx 7
bx 6
05
bx 4
bx 3
bx 2
bx 1
x0
bx /
bx .
x-
x,
x+
bx *
x)
0(
bx '
0&
0%
0$
0#
1"
x!
$end
#5000
1#
#7000
0`
0N
0<
0;
0M
0_
0+
0^
b0 j
b0 g
0,
0L
b0 X
b0 U
0-
0:
b0 F
b0 C
0!
00
0)
b0 /
b0 1
b0 6
b0 A
b0 H
b0 S
b0 Z
b0 e
b0 .
b0 2
b0 7
b0 D
b0 I
b0 V
b0 [
b0 h
b10 *
b10 3
b10 8
b10 J
b10 \
b1 '
b1 4
b1 9
b1 K
b1 ]
0"
#10000
0#
#15000
1#
#17000
1?
15
1(
1%
1"
#20000
0#
#25000
0?
1Q
05
1G
b10 '
b10 4
b10 9
b10 K
b10 ]
b1 /
b1 1
b1 6
b1 A
b1 H
b1 S
b1 Z
b1 e
b1 .
b1 2
b1 7
b1 D
b1 I
b1 V
b1 [
b1 h
1)
1#
#30000
1&
1$
0#
#35000
0Q
1c
1d
1M
0G
1Y
0R
b11 '
b11 4
b11 9
b11 K
b11 ]
b10 /
b10 1
b10 6
b10 A
b10 H
b10 S
b10 Z
b10 e
b10 .
b10 2
b10 7
b10 D
b10 I
b10 V
b10 [
b10 h
10
0)
1L
1#
#40000
0#
#45000
1_
1?
0c
15
0Y
0d
1^
b1 '
b1 4
b1 9
b1 K
b1 ]
b11 /
b11 1
b11 6
b11 A
b11 H
b11 S
b11 Z
b11 e
b11 .
b11 2
b11 7
b11 D
b11 I
b11 V
b11 [
b11 h
00
1)
1#
#50000
0#
#55000
0?
1Q
1R
1;
05
1G
0@
b10 '
b10 4
b10 9
b10 K
b10 ]
b0 /
b0 1
b0 6
b0 A
b0 H
b0 S
b0 Z
b0 e
b100 .
b100 2
b100 7
b100 D
b100 I
b100 V
b100 [
b100 h
10
0)
1:
1#
#60000
0#
#65000
0Q
1c
0G
1Y
0R
1,
b11 '
b11 4
b11 9
b11 K
b11 ]
b1 /
b1 1
b1 6
b1 A
b1 H
b1 S
b1 Z
b1 e
b101 .
b101 2
b101 7
b101 D
b101 I
b101 V
b101 [
b101 h
00
1)
1#
#70000
0#
#75000
1?
1@
0c
15
0Y
0d
1!
b1 '
b1 4
b1 9
b1 K
b1 ]
b10 /
b10 1
b10 6
b10 A
b10 H
b10 S
b10 Z
b10 e
b110 .
b110 2
b110 7
b110 D
b110 I
b110 V
b110 [
b110 h
10
0)
1#
#80000
0#
#85000
0?
1Q
05
1G
0@
1-
b10 '
b10 4
b10 9
b10 K
b10 ]
b11 /
b11 1
b11 6
b11 A
b11 H
b11 S
b11 Z
b11 e
b111 .
b111 2
b111 7
b111 D
b111 I
b111 V
b111 [
b111 h
00
1)
1#
#90000
0&
0$
0#
#95000
0Q
1c
1d
0M
0G
1Y
0R
b11 '
b11 4
b11 9
b11 K
b11 ]
b0 /
b0 1
b0 6
b0 A
b0 H
b0 S
b0 Z
b0 e
b1000 .
b1000 2
b1000 7
b1000 D
b1000 I
b1000 V
b1000 [
b1000 h
10
0)
0L
1#
#100000
1&
1$
0#
#105000
1?
0c
15
0Y
0d
1+
b1 '
b1 4
b1 9
b1 K
b1 ]
b1 /
b1 1
b1 6
b1 A
b1 H
b1 S
b1 Z
b1 e
b1001 .
b1001 2
b1001 7
b1001 D
b1001 I
b1001 V
b1001 [
b1001 h
00
1)
1#
#110000
0#
#115000
0?
1Q
1R
05
1G
0@
b10 '
b10 4
b10 9
b10 K
b10 ]
b10 /
b10 1
b10 6
b10 A
b10 H
b10 S
b10 Z
b10 e
b1010 .
b1010 2
b1010 7
b1010 D
b1010 I
b1010 V
b1010 [
b1010 h
10
0)
1#
#120000
0&
0$
0#
#125000
0Q
1c
0G
1Y
0R
b11 '
b11 4
b11 9
b11 K
b11 ]
b11 /
b11 1
b11 6
b11 A
b11 H
b11 S
b11 Z
b11 e
b1011 .
b1011 2
b1011 7
b1011 D
b1011 I
b1011 V
b1011 [
b1011 h
00
1)
1#
#130000
1&
1$
0#
#135000
1?
1@
0c
15
0Y
0d
b1 '
b1 4
b1 9
b1 K
b1 ]
b0 /
b0 1
b0 6
b0 A
b0 H
b0 S
b0 Z
b0 e
b1100 .
b1100 2
b1100 7
b1100 D
b1100 I
b1100 V
b1100 [
b1100 h
10
0)
1#
#140000
0#
#145000
0?
1Q
05
1G
0@
0-
b10 '
b10 4
b10 9
b10 K
b10 ]
b1 /
b1 1
b1 6
b1 A
b1 H
b1 S
b1 Z
b1 e
b1101 .
b1101 2
b1101 7
b1101 D
b1101 I
b1101 V
b1101 [
b1101 h
00
1)
1#
#150000
0&
0$
0#
#155000
0Q
1c
1d
0G
1Y
0R
b11 '
b11 4
b11 9
b11 K
b11 ]
b10 /
b10 1
b10 6
b10 A
b10 H
b10 S
b10 Z
b10 e
b1110 .
b1110 2
b1110 7
b1110 D
b1110 I
b1110 V
b1110 [
b1110 h
10
0)
1#
#160000
1&
1$
0#
#165000
1?
0c
15
0Y
0d
0+
b1 '
b1 4
b1 9
b1 K
b1 ]
b11 /
b11 1
b11 6
b11 A
b11 H
b11 S
b11 Z
b11 e
b1111 .
b1111 2
b1111 7
b1111 D
b1111 I
b1111 V
b1111 [
b1111 h
00
1)
1#
#170000
0&
0$
0#
#175000
0?
1Q
1R
0;
05
1G
0@
b10 '
b10 4
b10 9
b10 K
b10 ]
b0 /
b0 1
b0 6
b0 A
b0 H
b0 S
b0 Z
b0 e
b0 .
b0 2
b0 7
b0 D
b0 I
b0 V
b0 [
b0 h
10
0)
0:
1#
#180000
1&
1$
0#
#185000
1M
0Q
1c
0G
1Y
0R
1L
b11 '
b11 4
b11 9
b11 K
b11 ]
b1 /
b1 1
b1 6
b1 A
b1 H
b1 S
b1 Z
b1 e
b1 .
b1 2
b1 7
b1 D
b1 I
b1 V
b1 [
b1 h
00
1)
1#
#190000
0&
0$
0#
#195000
1?
1@
0c
0_
15
0Y
0d
b1 '
b1 4
b1 9
b1 K
b1 ]
b10 /
b10 1
b10 6
b10 A
b10 H
b10 S
b10 Z
b10 e
b10 .
b10 2
b10 7
b10 D
b10 I
b10 V
b10 [
b10 h
10
0)
0^
1#
#200000
1&
1$
0#
#205000
1;
0?
1Q
05
1G
0@
1:
b10 '
b10 4
b10 9
b10 K
b10 ]
b11 /
b11 1
b11 6
b11 A
b11 H
b11 S
b11 Z
b11 e
b11 .
b11 2
b11 7
b11 D
b11 I
b11 V
b11 [
b11 h
00
1)
1#
#210000
0#
#215000
0Q
1c
1d
0G
1Y
0R
b11 '
b11 4
b11 9
b11 K
b11 ]
b0 /
b0 1
b0 6
b0 A
b0 H
b0 S
b0 Z
b0 e
b100 .
b100 2
b100 7
b100 D
b100 I
b100 V
b100 [
b100 h
10
0)
1#
#220000
0&
0$
0#
#225000
1?
0c
15
0Y
0d
b1 '
b1 4
b1 9
b1 K
b1 ]
b1 /
b1 1
b1 6
b1 A
b1 H
b1 S
b1 Z
b1 e
b101 .
b101 2
b101 7
b101 D
b101 I
b101 V
b101 [
b101 h
00
1)
1#
#230000
1&
1$
0#
#235000
0?
1Q
1R
05
1G
0@
b10 '
b10 4
b10 9
b10 K
b10 ]
b10 /
b10 1
b10 6
b10 A
b10 H
b10 S
b10 Z
b10 e
b110 .
b110 2
b110 7
b110 D
b110 I
b110 V
b110 [
b110 h
10
0)
1#
#240000
0&
0$
0#
#245000
0M
0Q
1c
0G
1Y
0R
0,
0L
b11 '
b11 4
b11 9
b11 K
b11 ]
b11 /
b11 1
b11 6
b11 A
b11 H
b11 S
b11 Z
b11 e
b111 .
b111 2
b111 7
b111 D
b111 I
b111 V
b111 [
b111 h
00
1)
1#
#250000
0#
#255000
1?
1@
0c
15
0Y
0d
0!
b1 '
b1 4
b1 9
b1 K
b1 ]
b0 /
b0 1
b0 6
b0 A
b0 H
b0 S
b0 Z
b0 e
b1000 .
b1000 2
b1000 7
b1000 D
b1000 I
b1000 V
b1000 [
b1000 h
10
0)
1#
#260000
0#
#265000
0;
0?
1Q
05
1G
0@
1-
0:
b10 '
b10 4
b10 9
b10 K
b10 ]
b1 /
b1 1
b1 6
b1 A
b1 H
b1 S
b1 Z
b1 e
b1001 .
b1001 2
b1001 7
b1001 D
b1001 I
b1001 V
b1001 [
b1001 h
00
1)
1#
#270000
1&
1$
0#
#275000
0Q
1c
1d
1M
0G
1Y
0R
1!
b11 '
b11 4
b11 9
b11 K
b11 ]
b10 /
b10 1
b10 6
b10 A
b10 H
b10 S
b10 Z
b10 e
b1010 .
b1010 2
b1010 7
b1010 D
b1010 I
b1010 V
b1010 [
b1010 h
10
0)
1L
1#
#280000
0&
0$
0#
#285000
1?
0c
15
0Y
0d
b1 '
b1 4
b1 9
b1 K
b1 ]
b11 /
b11 1
b11 6
b11 A
b11 H
b11 S
b11 Z
b11 e
b1011 .
b1011 2
b1011 7
b1011 D
b1011 I
b1011 V
b1011 [
b1011 h
00
1)
1#
#290000
1&
1$
0#
#295000
0?
1Q
1R
1;
05
1G
0@
b10 '
b10 4
b10 9
b10 K
b10 ]
b0 /
b0 1
b0 6
b0 A
b0 H
b0 S
b0 Z
b0 e
b1100 .
b1100 2
b1100 7
b1100 D
b1100 I
b1100 V
b1100 [
b1100 h
10
0)
1:
1#
#300000
0#
#305000
0Q
1c
0G
1Y
0R
1,
b11 '
b11 4
b11 9
b11 K
b11 ]
b1 /
b1 1
b1 6
b1 A
b1 H
b1 S
b1 Z
b1 e
b1101 .
b1101 2
b1101 7
b1101 D
b1101 I
b1101 V
b1101 [
b1101 h
00
1)
1#
#310000
0#
#315000
1?
1@
0c
1_
15
0Y
0d
b1 '
b1 4
b1 9
b1 K
b1 ]
b10 /
b10 1
b10 6
b10 A
b10 H
b10 S
b10 Z
b10 e
b1110 .
b1110 2
b1110 7
b1110 D
b1110 I
b1110 V
b1110 [
b1110 h
10
0)
1^
1#
#320000
0?
0@
05
0(
0%
0#
#325000
1#
#330000
0#
#335000
1#
#340000
0#
#345000
1#
#350000
0#
#355000
1#
#360000
1B
1@
0&
0$
15
0;
0M
0_
0#
1(
1%
b0 *
b0 3
b0 8
b0 J
b0 \
#365000
0B
1T
05
1G
0@
b10 '
b10 4
b10 9
b10 K
b10 ]
b11 /
b11 1
b11 6
b11 A
b11 H
b11 S
b11 Z
b11 e
b1111 .
b1111 2
b1111 7
b1111 D
b1111 I
b1111 V
b1111 [
b1111 h
00
1)
1#
#370000
1&
1$
0#
#375000
0T
1f
1d
0G
1Y
0R
b11 '
b11 4
b11 9
b11 K
b11 ]
b0 /
b0 1
b0 6
b0 A
b0 H
b0 S
b0 Z
b0 e
b0 .
b0 2
b0 7
b0 D
b0 I
b0 V
b0 [
b0 h
10
0)
b1 U
1#
#380000
0&
0$
0#
#385000
1B
0f
15
0Y
0d
b1 '
b1 4
b1 9
b1 K
b1 ]
b1 /
b1 1
b1 6
b1 A
b1 H
b1 S
b1 Z
b1 e
b1 .
b1 2
b1 7
b1 D
b1 I
b1 V
b1 [
b1 h
00
1)
1#
#390000
1&
1$
0#
#395000
0B
1T
1R
05
1G
0@
b10 '
b10 4
b10 9
b10 K
b10 ]
b10 /
b10 1
b10 6
b10 A
b10 H
b10 S
b10 Z
b10 e
b10 .
b10 2
b10 7
b10 D
b10 I
b10 V
b10 [
b10 h
10
0)
b1 C
1#
#400000
0&
0$
0#
#405000
0T
1f
0G
1Y
0R
b10 U
b11 '
b11 4
b11 9
b11 K
b11 ]
b11 /
b11 1
b11 6
b11 A
b11 H
b11 S
b11 Z
b11 e
b11 .
b11 2
b11 7
b11 D
b11 I
b11 V
b11 [
b11 h
00
1)
1#
#410000
1&
1$
0#
#415000
1B
1@
0f
15
0Y
0d
b1 '
b1 4
b1 9
b1 K
b1 ]
b0 /
b0 1
b0 6
b0 A
b0 H
b0 S
b0 Z
b0 e
b100 .
b100 2
b100 7
b100 D
b100 I
b100 V
b100 [
b100 h
10
0)
b1 g
1#
#420000
0&
0$
0#
#425000
0B
1T
05
1G
0@
b10 C
b10 '
b10 4
b10 9
b10 K
b10 ]
b1 /
b1 1
b1 6
b1 A
b1 H
b1 S
b1 Z
b1 e
b101 .
b101 2
b101 7
b101 D
b101 I
b101 V
b101 [
b101 h
00
1)
1#
#430000
1&
1$
0#
#435000
0T
1f
1d
0G
1Y
0R
b11 '
b11 4
b11 9
b11 K
b11 ]
b10 /
b10 1
b10 6
b10 A
b10 H
b10 S
b10 Z
b10 e
b110 .
b110 2
b110 7
b110 D
b110 I
b110 V
b110 [
b110 h
10
0)
b101 U
1#
#440000
0&
0$
0#
#445000
1B
0f
15
0Y
0d
b10 g
b1 '
b1 4
b1 9
b1 K
b1 ]
b11 /
b11 1
b11 6
b11 A
b11 H
b11 S
b11 Z
b11 e
b111 .
b111 2
b111 7
b111 D
b111 I
b111 V
b111 [
b111 h
00
1)
1#
#450000
1&
1$
0#
#455000
0B
1T
1R
05
1G
0@
b10 '
b10 4
b10 9
b10 K
b10 ]
b0 /
b0 1
b0 6
b0 A
b0 H
b0 S
b0 Z
b0 e
b1000 .
b1000 2
b1000 7
b1000 D
b1000 I
b1000 V
b1000 [
b1000 h
10
0)
b101 C
1#
#460000
0&
0$
0#
